eweb.py
eweb-0.0.1.dist-info/METADATA
eweb-0.0.1.dist-info/WHEEL
eweb-0.0.1.dist-info/top_level.txt
eweb-0.0.1.dist-info/RECORD
