Metadata-Version: 2.1
Name: eweb
Version: 0.0.1
Summary: a fast and simple micro-framework for small web applications
Home-page: https://github.com/lixk/eweb
Author: Xiangkui Li
Author-email: 1749498702@qq.com
License: MIT Licence
Keywords: pip,eweb
Platform: any
Requires-Dist: bottle
Requires-Dist: waitress
